bellek/__init__.py
bellek/_modidx.py
bellek/ds.py
bellek/logging.py
bellek/testing.py
bellek/utils.py
bellek/wandb.py
bellek/dspy/__init__.py
bellek/dspy/predict/__init__.py
bellek/dspy/predict/cte.py
bellek/dvc/__init__.py
bellek/dvc/experiment.py
bellek/hf/__init__.py
bellek/hf/datasets/__init__.py
bellek/hf/datasets/utils.py
bellek/hf/transformers/__init__.py
bellek/hf/transformers/experiment.py
bellek/hf/transformers/generation.py
bellek/hf/transformers/llama3.py
bellek/hf/transformers/utils.py
bellek/jerx/__init__.py
bellek/jerx/eval.py
bellek/jerx/prompt.py
bellek/jerx/utils.py
bellek/jerx/dataset/__init__.py
bellek/jerx/dataset/docred.py
bellek/jerx/dataset/webnlg.py
bellek/jerx/fewshot/__init__.py
bellek/jerx/fewshot/llm.py
bellek/jerx/offline/__init__.py
bellek/jerx/offline/llm.py
bellek/jerx/reward/__init__.py
bellek/jerx/reward/heuristic.py
bellek/jerx/reward/llm.py
bellek/jerx/reward/qa.py
bellek/lang/__init__.py
bellek/lang/dataset.py
bellek/lang/qdecomp.py
bellek/llama_index/__init__.py
bellek/llama_index/obs.py
bellek/llama_index/data_structs/__init__.py
bellek/llama_index/data_structs/data_structs.py
bellek/llama_index/graph_stores/__init__.py
bellek/llama_index/graph_stores/kuzu.py
bellek/llama_index/indices/__init__.py
bellek/llama_index/indices/knowledge_graph/__init__.py
bellek/llama_index/indices/knowledge_graph/base.py
bellek/llama_index/indices/knowledge_graph/retrievers.py
bellek/mhqa/__init__.py
bellek/mhqa/llm.py
bellek/ml/__init__.py
bellek/ml/clip.py
bellek/ml/coop.py
bellek/ml/data.py
bellek/ml/evaluation.py
bellek/ml/experiment.py
bellek/ml/layer.py
bellek/ml/loss.py
bellek/ml/mcd.py
bellek/ml/vision.py
bellek/musique/__init__.py
bellek/musique/baseline.py
bellek/musique/constants.py
bellek/musique/eval.py
bellek/musique/multihop.py
bellek/musique/multihopjerx.py
bellek/musique/nhop.py
bellek/musique/qa.py
bellek/musique/singlehop.py
bellek/qa/__init__.py
bellek/qa/ablation.py
bellek/qa/llm.py
bellek/qdecomp/__init__.py
bellek-0.133.0.dist-info/LICENSE
bellek-0.133.0.dist-info/METADATA
bellek-0.133.0.dist-info/WHEEL
bellek-0.133.0.dist-info/entry_points.txt
bellek-0.133.0.dist-info/top_level.txt
bellek-0.133.0.dist-info/RECORD
