Metadata-Version: 2.1
Name: bellek
Version: 0.133.0
Summary: My digital memory
Home-page: https://github.com/bdsaglam/bellek
Author: Barış Deniz Sağlam
Author-email: bdsaglam@gmail.com
License: Apache Software License 2.0
Keywords: notebook
Classifier: Development Status :: 4 - Beta
Classifier: Intended Audience :: Developers
Classifier: Natural Language :: English
Classifier: Programming Language :: Python :: 3.10
Classifier: License :: OSI Approved :: Apache Software License
Requires-Python: >=3.10
License-File: LICENSE
Requires-Dist: numpy >=1.26.2
Requires-Dist: pandas >=2.1.4
Requires-Dist: datasets >=2.15.0
Requires-Dist: evaluate >=0.4.1
Requires-Dist: fastcore >=1.5.29
Requires-Dist: fastai >=2.7.11
Requires-Dist: fastmtl >=1.2.0
Requires-Dist: instructor >=1.3.3
Requires-Dist: sentence-transformers >=2.2.2
Requires-Dist: transformers >=4.39.3
Requires-Dist: text-generation ~=0.6.1
Requires-Dist: arize-phoenix ~=2.1.0
Requires-Dist: python-dotenv
Requires-Dist: wandb
Requires-Dist: tqdm
Requires-Dist: dspy-ai
Provides-Extra: dev
Requires-Dist: nbdev ; extra == 'dev'
Requires-Dist: jupyter ; extra == 'dev'
Requires-Dist: twine ; extra == 'dev'
Requires-Dist: pre-commit ; extra == 'dev'
Requires-Dist: isort ; extra == 'dev'
Requires-Dist: black ; extra == 'dev'
Requires-Dist: dvc >=3.55.2 ; extra == 'dev'
Requires-Dist: dvc-s3 >=3.2.0 ; extra == 'dev'
Requires-Dist: huggingface-hub ; extra == 'dev'
Requires-Dist: typer ; extra == 'dev'
Requires-Dist: rich ; extra == 'dev'
